ShiVec.py
ShiVec-0.2.1.dist-info/METADATA
ShiVec-0.2.1.dist-info/WHEEL
ShiVec-0.2.1.dist-info/top_level.txt
ShiVec-0.2.1.dist-info/RECORD
