Metadata-Version: 2.1
Name: ShiVec
Version: 0.2.1
Summary: ShiVec is a simple python package for working with vectors.
Home-page: https://github.com/ShisatOwO/ShiVec
Author: Shisato
Author-email: UNKNOWN
License: MIT License
Platform: UNKNOWN
